{"cameraMode":{"drawMode":0,"name":"Shaded","section":"Shading Mode"},"sceneLighting":false,"audioPlay":false,"sceneViewState":{"showFog":true,"showMaterialUpdate":false,"showSkybox":false,"showFlares":true,"showImageEffects":true,"showParticleSystems":true},"in2DMode":false,"pivot":{"x":0.013484110124409199,"y":-0.22190174460411073,"z":-0.2584889233112335},"rotation":{"x":-0.03905046358704567,"y":-0.9571014642715454,"z":0.24215641617774964,"w":-0.15435703098773957},"size":2.5377721786499025,"orthographic":false}